odoo10_addon_business_requirement-10.0.1.2.0-py2.7-nspkg.pth
odoo/addons/business_requirement/README.rst
odoo/addons/business_requirement/__init__.py
odoo/addons/business_requirement/__manifest__.py
odoo/addons/business_requirement/data/br_report_paperformat.xml
odoo/addons/business_requirement/data/business_data.xml
odoo/addons/business_requirement/data/business_requirement_demo.xml
odoo/addons/business_requirement/i18n/es.po
odoo/addons/business_requirement/i18n/fr_FR.po
odoo/addons/business_requirement/i18n/sl.po
odoo/addons/business_requirement/migrations/8.0.5.1.3/post-br-populate-responsible.py
odoo/addons/business_requirement/models/__init__.py
odoo/addons/business_requirement/models/business.py
odoo/addons/business_requirement/models/project.py
odoo/addons/business_requirement/report/report.xml
odoo/addons/business_requirement/security/ir.model.access.csv
odoo/addons/business_requirement/security/security.xml
odoo/addons/business_requirement/static/description/icon.png
odoo/addons/business_requirement/static/img/br_workflow.graphml
odoo/addons/business_requirement/static/img/bus_req.png
odoo/addons/business_requirement/static/img/bus_req_alias.png
odoo/addons/business_requirement/static/img/bus_req_approved.png
odoo/addons/business_requirement/static/img/bus_req_cancel.png
odoo/addons/business_requirement/static/img/bus_req_confirmed.png
odoo/addons/business_requirement/static/img/bus_req_cust_story.png
odoo/addons/business_requirement/static/img/bus_req_done.png
odoo/addons/business_requirement/static/img/bus_req_drop.png
odoo/addons/business_requirement/static/img/bus_req_module_diag.png
odoo/addons/business_requirement/static/img/bus_req_tags.png
odoo/addons/business_requirement/static/img/bus_req_tags2.png
odoo/addons/business_requirement/static/img/bus_req_tree.png
odoo/addons/business_requirement/static/img/bus_req_workflow.png
odoo/addons/business_requirement/static/img/module_diag.graphml
odoo10_addon_business_requirement-10.0.1.2.0.dist-info/DESCRIPTION.rst
odoo10_addon_business_requirement-10.0.1.2.0.dist-info/METADATA
odoo10_addon_business_requirement-10.0.1.2.0.dist-info/RECORD
odoo10_addon_business_requirement-10.0.1.2.0.dist-info/WHEEL
odoo10_addon_business_requirement-10.0.1.2.0.dist-info/metadata.json
odoo10_addon_business_requirement-10.0.1.2.0.dist-info/namespace_packages.txt
odoo10_addon_business_requirement-10.0.1.2.0.dist-info/top_level.txt
